Lab_3/exercise3.v
module exercise3(f, x1, x2, x3, x4);
input x1, x2, x3, x4;
output f;
assign f = (x1 & x2 & x4) | (x1 & x3 & x4) | (x1 & x2 & x3) | (x2 & x3 & x4);
endmodule

Lab_3/exercise3_tb.v
`timescale 1ns/1ns
`include "exercise3.v"

module exercise3_tb();

reg x1, x2, x3, x4;
wire f;

exercise3 test(f, x1, x2, x3, x4);
initial begin
        $dumpfile("exercise3.vcd");
        $dumpvars(0, exercise3_tb);
        
        x1 = 0; x2 = 0; x3 = 0; x4 = 0; #10;
        x1 = 0; x2 = 0; x3 = 0; x4 = 1; #10;
        x1 = 0; x2 = 0; x3 = 1; x4 = 0; #10;
        x1 = 0; x2 = 0; x3 = 1; x4 = 1; #10;
        x1 = 0; x2 = 1; x3 = 0; x4 = 0; #10;
        x1 = 0; x2 = 1; x3 = 0; x4 = 1; #10;
        x1 = 0; x2 = 1; x3 = 1; x4 = 0; #10;
        x1 = 0; x2 = 1; x3 = 1; x4 = 1; #10;
        x1 = 1; x2 = 0; x3 = 0; x4 = 0; #10;
        x1 = 1; x2 = 0; x3 = 0; x4 = 1; #10;
        x1 = 1; x2 = 0; x3 = 1; x4 = 0; #10;
        x1 = 1; x2 = 0; x3 = 1; x4 = 1; #10;
        x1 = 1; x2 = 1; x3 = 0; x4 = 0; #10;
        x1 = 1; x2 = 1; x3 = 0; x4 = 1; #10;
        x1 = 1; x2 = 1; x3 = 1; x4 = 0; #10;
        x1 = 1; x2 = 1; x3 = 1; x4 = 1; #10;
               
        $display("Test Complete");
end
endmodule

Lab_3/exercise3.vcd
$date
	Tue Sep  6 10:29:49 2022
$end
$version
	Icarus Verilog
$end
$timescale
	1ns
$end
$scope module exercise3_tb $end
$var wire 1 ! f $end
$var reg 1 " x1 $end
$var reg 1 # x2 $end
$var reg 1 $ x3 $end
$var reg 1 % x4 $end
$scope module test $end
$var wire 1 ! f $end
$var wire 1 " x1 $end
$var wire 1 # x2 $end
$var wire 1 $ x3 $end
$var wire 1 % x4 $end
$upscope $end
$upscope $end
$enddefinitions $end
#0
$dumpvars
0%
0$
0#
0"
0!
$end
#10
1%
#20
0%
1$
#30
1%
#40
0%
0$
1#
#50
1%
#60
0%
1$
#70
1!
1%
#80
0!
0%
0$
0#
1"
#90
1%
#100
0%
1$
#110
1!
1%
#120
0!
0%
0$
1#
#130
1!
1%
#140
0%
1$
#150
1%
