Lab_3/exercise2a.v
module exercise2a(f, a, b, c, d);
input a, b, c, d;
output f;
assign f = (b | c) & ((~b) | d);
endmodule

Lab_3/exercise2a_tb.v
`timescale 1ns/1ns
`include "exercise2a.v"

module exercise2a_tb();

reg a, b, c, d;
wire f;

exercise2a test(f, a, b, c, d);
initial begin
        $dumpfile("exercise2a.vcd");
        $dumpvars(0, exercise2a_tb);
        
        a = 0; b = 0; c = 0; d = 0; #10;
        a = 0; b = 0; c = 0; d = 1; #10;
        a = 0; b = 0; c = 1; d = 0; #10;
        a = 0; b = 0; c = 1; d = 1; #10;
        a = 0; b = 1; c = 0; d = 0; #10;
        a = 0; b = 1; c = 0; d = 1; #10;
        a = 0; b = 1; c = 1; d = 0; #10;
        a = 0; b = 1; c = 1; d = 1; #10;
        a = 1; b = 0; c = 0; d = 0; #10;
        a = 1; b = 0; c = 0; d = 1; #10;
        a = 1; b = 0; c = 1; d = 0; #10;
        a = 1; b = 0; c = 1; d = 1; #10;
        a = 1; b = 1; c = 0; d = 0; #10;
        a = 1; b = 1; c = 0; d = 1; #10;
        a = 1; b = 1; c = 1; d = 0; #10;
        a = 1; b = 1; c = 1; d = 1; #10;
        
        $display("Test Complete");
end
endmodule

Lab_3/exercise2a.vcd
$date
	Tue Sep  6 09:46:47 2022
$end
$version
	Icarus Verilog
$end
$timescale
	1ns
$end
$scope module exercise2a_tb $end
$var wire 1 ! f $end
$var reg 1 " a $end
$var reg 1 # b $end
$var reg 1 $ c $end
$var reg 1 % d $end
$scope module test $end
$var wire 1 " a $end
$var wire 1 # b $end
$var wire 1 $ c $end
$var wire 1 % d $end
$var wire 1 ! f $end
$upscope $end
$upscope $end
$enddefinitions $end
#0
$dumpvars
0%
0$
0#
0"
0!
$end
#10
1%
#20
1!
0%
1$
#30
1%
#40
0!
0%
0$
1#
#50
1!
1%
#60
0!
0%
1$
#70
1!
1%
#80
0!
0%
0$
0#
1"
#90
1%
#100
1!
0%
1$
#110
1%
#120
0!
0%
0$
1#
#130
1!
1%
#140
0!
0%
1$
#150
1!
1%
