Lab_5/dec4to16e2.v
module dec4to16e2(A, En, D);
input [3:0]A;
input En;
output [0:15]D;

dec3to8 d1(A[2:0], En&(~A[3]), D[0:7]);
dec3to8 d2(A[2:0], En&A[3], D[8:15]);

endmodule


module dec3to8(A, En, D);
input [2:0]A;
input En;
output reg [0:7]D;
integer k;

always@(A or En)
begin 
        for (k = 0; k < 8; k++)
                if ((A == k) && (En == 1))
                        D[k] = 1;
                else
                        D[k] = 0;
end
endmodule

Lab_5/exercise2_tb.v
/* Lab Exercise 2
        Write behavioral Verilog code for a 3 to 8 decoder with active-high enable input and active high output
using for loop. Using the 3 to 8 decoders above, design a 4 to 16 decoder and write the Verilog code
for the same.
*/

`timescale 1ns/1ns
`include "dec4to16e2.v"

module exercise2_tb();

reg [3:0]A;
reg En;
wire [0:15]D;
integer i;

dec4to16e2 test(A, En, D);
initial begin 
        $dumpfile("exercise2.vcd");
        $dumpvars(0, exercise2_tb);
        
        En = 0;
        for(i=0; i<16; i++)
        begin 
                A = i; #10;
        end
        
        En = 1;
        for(i=0; i<16; i++)
        begin 
                A = i; #10;
        end
        
        $display("Test Complete"); 
end
endmodule

Lab_5/exercise2.vcd
$date
	Tue Oct 11 09:25:42 2022
$end
$version
	Icarus Verilog
$end
$timescale
	1ns
$end
$scope module exercise2_tb $end
$var wire 16 ! D [0:15] $end
$var reg 4 " A [3:0] $end
$var reg 1 # En $end
$var integer 32 $ i [31:0] $end
$scope module test $end
$var wire 4 % A [3:0] $end
$var wire 1 # En $end
$var wire 16 & D [0:15] $end
$scope module d1 $end
$var wire 3 ' A [2:0] $end
$var wire 1 ( En $end
$var reg 8 ) D [0:7] $end
$var integer 32 * k [31:0] $end
$upscope $end
$scope module d2 $end
$var wire 3 + A [2:0] $end
$var wire 1 , En $end
$var reg 8 - D [0:7] $end
$var integer 32 . k [31:0] $end
$upscope $end
$upscope $end
$upscope $end
$enddefinitions $end
#0
$dumpvars
b1000 .
b0 -
0,
b0 +
b1000 *
b0 )
0(
b0 '
b0 &
b0 %
b0 $
0#
b0 "
b0 !
$end
#10
b1000 *
b1000 .
b1 '
b1 +
b1 "
b1 %
b1 $
#20
b1000 *
b1000 .
b10 '
b10 +
b10 "
b10 %
b10 $
#30
b1000 *
b1000 .
b11 '
b11 +
b11 "
b11 %
b11 $
#40
b1000 *
b1000 .
b100 '
b100 +
b100 "
b100 %
b100 $
#50
b1000 *
b1000 .
b101 '
b101 +
b101 "
b101 %
b101 $
#60
b1000 *
b1000 .
b110 '
b110 +
b110 "
b110 %
b110 $
#70
b1000 *
b1000 .
b111 '
b111 +
b111 "
b111 %
b111 $
#80
b1000 *
b1000 .
b0 '
b0 +
b1000 "
b1000 %
b1000 $
#90
b1000 *
b1000 .
b1 '
b1 +
b1001 "
b1001 %
b1001 $
#100
b1000 *
b1000 .
b10 '
b10 +
b1010 "
b1010 %
b1010 $
#110
b1000 *
b1000 .
b11 '
b11 +
b1011 "
b1011 %
b1011 $
#120
b1000 *
b1000 .
b100 '
b100 +
b1100 "
b1100 %
b1100 $
#130
b1000 *
b1000 .
b101 '
b101 +
b1101 "
b1101 %
b1101 $
#140
b1000 *
b1000 .
b110 '
b110 +
b1110 "
b1110 %
b1110 $
#150
b1000 *
b1000 .
b111 '
b111 +
b1111 "
b1111 %
b1111 $
#160
b10000000 )
1(
b1000 *
b1000000000000000 !
b1000000000000000 &
b0 -
b1000 .
b0 '
b0 +
0,
b0 "
b0 %
1#
b0 $
#170
b100000000000000 !
b100000000000000 &
b1000000 )
b1000 *
b1000 .
b1 '
b1 +
b1 "
b1 %
b1 $
#180
b10000000000000 !
b10000000000000 &
b100000 )
b1000 *
b1000 .
b10 '
b10 +
b10 "
b10 %
b10 $
#190
b1000000000000 !
b1000000000000 &
b10000 )
b1000 *
b1000 .
b11 '
b11 +
b11 "
b11 %
b11 $
#200
b100000000000 !
b100000000000 &
b1000 )
b1000 *
b1000 .
b100 '
b100 +
b100 "
b100 %
b100 $
#210
b10000000000 !
b10000000000 &
b100 )
b1000 *
b1000 .
b101 '
b101 +
b101 "
b101 %
b101 $
#220
b1000000000 !
b1000000000 &
b10 )
b1000 *
b1000 .
b110 '
b110 +
b110 "
b110 %
b110 $
#230
b100000000 !
b100000000 &
b1 )
b1000 *
b1000 .
b111 '
b111 +
b111 "
b111 %
b111 $
#240
0(
b0 )
b1000 *
b10000000 !
b10000000 &
b10000000 -
b1000 .
1,
b0 '
b0 +
b1000 "
b1000 %
b1000 $
#250
b1000 *
b1000000 !
b1000000 &
b1000000 -
b1000 .
b1 '
b1 +
b1001 "
b1001 %
b1001 $
#260
b1000 *
b100000 !
b100000 &
b100000 -
b1000 .
b10 '
b10 +
b1010 "
b1010 %
b1010 $
#270
b1000 *
b10000 !
b10000 &
b10000 -
b1000 .
b11 '
b11 +
b1011 "
b1011 %
b1011 $
#280
b1000 *
b1000 !
b1000 &
b1000 -
b1000 .
b100 '
b100 +
b1100 "
b1100 %
b1100 $
#290
b1000 *
b100 !
b100 &
b100 -
b1000 .
b101 '
b101 +
b1101 "
b1101 %
b1101 $
#300
b1000 *
b10 !
b10 &
b10 -
b1000 .
b110 '
b110 +
b1110 "
b1110 %
b1110 $
#310
b1000 *
b1 !
b1 &
b1 -
b1000 .
b111 '
b111 +
b1111 "
b1111 %
b1111 $
#320
b10000 $
