Lab_2/exercise2_2.v
module exercise2_2(f, g, h, x, y, z);
input x, y, z;
output f, g, h;

// Given Expression
assign f = y | (x & (~z));

// Using NOR Gates only
nor(i1, x, x);
nor(i2, i1, z);
nor(i3, y, i2);
nor(g, i3, i3);

// Using NAND Gates only
nand(j1, z, z);
nand(j2, x, j1);
nand(j3, y, y);
nand(h, j2, j3);

endmodule

Lab_2/exercise2_2_tb.v
`timescale 1ns/1ns
`include "exercise2_2.v"

module exercise2_2_tb;

reg x, y, z;
wire f, g, h;

exercise2_2 test(f, g, h, x, y, z);
initial begin 
        $dumpfile("exercise2_2.vcd");
        $dumpvars(0, exercise2_2_tb);
        
        x = 0; y = 0; z = 0; #10;
        x = 0; y = 0; z = 1; #10;
        x = 0; y = 1; z = 0; #10;
        x = 0; y = 1; z = 1; #10;
        x = 1; y = 0; z = 0; #10;
        x = 1; y = 0; z = 1; #10;
        x = 1; y = 1; z = 0; #10;
        x = 1; y = 1; z = 1; #10;
        
        $display("Test Complete");
end 
endmodule

Lab_2/exercise2_2.vcd
$date
	Tue Aug 30 10:42:52 2022
$end
$version
	Icarus Verilog
$end
$timescale
	1ns
$end
$scope module exercise2_2_tb $end
$var wire 1 ! h $end
$var wire 1 " g $end
$var wire 1 # f $end
$var reg 1 $ x $end
$var reg 1 % y $end
$var reg 1 & z $end
$scope module test $end
$var wire 1 # f $end
$var wire 1 " g $end
$var wire 1 ! h $end
$var wire 1 ' i1 $end
$var wire 1 ( i2 $end
$var wire 1 ) i3 $end
$var wire 1 * j1 $end
$var wire 1 + j2 $end
$var wire 1 , j3 $end
$var wire 1 $ x $end
$var wire 1 % y $end
$var wire 1 & z $end
$upscope $end
$upscope $end
$enddefinitions $end
#0
$dumpvars
1,
1+
1*
1)
0(
1'
0&
0%
0$
0#
0"
0!
$end
#10
0*
1&
#20
1"
1!
1*
1#
0)
0,
0&
1%
#30
0*
1&
#40
0+
1"
1!
1(
1*
1#
0)
1,
0'
0&
0%
1$
#50
0#
0"
0!
1)
1+
0(
0*
1&
#60
0+
1"
1!
1(
1*
1#
0)
0,
0&
1%
#70
1+
0(
0*
1&
