Lab_2/exercise1ii.v
module exercise1ii(f, g, x, y, z);
input x, y, z;
output f, g;
assign f = x & (y | z);
assign g = (x & y) | (x & z);
endmodule

Lab_2/exercise1ii_tb.v
`timescale 1ns/1ns
`include "exercise1ii.v"

module exercise1ii_tb;

reg x, y, z;
wire f, g;

exercise1ii test(f, g, x, y, z);
initial begin
	$dumpfile("exercise1ii.vcd");
	$dumpvars(0, exercise1ii_tb);

	x = 0; y = 0; z = 0; #10;
	x = 0; y = 0; z = 1; #10;
	x = 0; y = 1; z = 0; #10;
	x = 0; y = 1; z = 1; #10;
	x = 1; y = 0; z = 0; #10;
	x = 1; y = 0; z = 1; #10;
	x = 1; y = 1; z = 0; #10;
	x = 1; y = 1; z = 1; #10;

	$display("Test Complete");
end
endmodule

Lab_2/exercise1ii.vcd
$date
	Tue Aug 30 08:55:34 2022
$end
$version
	Icarus Verilog
$end
$timescale
	1ns
$end
$scope module exercise1ii_tb $end
$var wire 1 ! g $end
$var wire 1 " f $end
$var reg 1 # x $end
$var reg 1 $ y $end
$var reg 1 % z $end
$scope module test $end
$var wire 1 " f $end
$var wire 1 ! g $end
$var wire 1 # x $end
$var wire 1 $ y $end
$var wire 1 % z $end
$upscope $end
$upscope $end
$enddefinitions $end
#0
$dumpvars
0%
0$
0#
0"
0!
$end
#10
1%
#20
0%
1$
#30
1%
#40
0"
0%
0$
1#
#50
1"
1!
1%
#60
0%
1$
#70
1%
