Lab_2/exercise2_3.v
module exercise2_3(f, g, h, x1, x2, x3);
input x1, x2, x3;
output f, g, h;

// Given Expression
assign f = (x1 | x2) & ((~x1) | (~x3));

// Using NOR Gates only
nor(i1, x1, x2);
nor(i3, x1, x1);
nor(i4, x3, x3);
nor(i5, i3, i4);
nor(g, i3, i5);

// Using NAND Gates only
nand(j1, x1, x1);
nand(j2, x2, x2);
nand(j3, j1, j2);

nand(j4, x1, x1);
nand(j5, x3, x3);
nand(j6, j4, j4);
nand(j7, j6, j6);

nand(j8, j3, j7);
nand(h, j8, j8);

endmodule

Lab_2/exercise2_3_tb.v
`timescale 1ns/1ns
`include "exercise2_3.v"

module exercise2_3_tb;

reg x1, x2, x3;
wire f, g, h;

exercise2_3 test(f, g, h, x1, x2, x3);
initial begin 
        $dumpfile("exercise2_3.vcd");
        $dumpvars(0, exercise2_3_tb);
        
        x1 = 0; x2 = 0; x3 = 0; #10;
        x1 = 0; x2 = 0; x3 = 1; #10;
        x1 = 0; x2 = 1; x3 = 0; #10;
        x1 = 0; x2 = 1; x3 = 1; #10;
        x1 = 1; x2 = 0; x3 = 0; #10;
        x1 = 1; x2 = 0; x3 = 1; #10;
        x1 = 1; x2 = 1; x3 = 0; #10;
        x1 = 1; x2 = 1; x3 = 1; #10;
        
        $display("Test Complete");
end 
endmodule

Lab_2/exercise2_3.vcd
$date
	Tue Aug 30 11:31:22 2022
$end
$version
	Icarus Verilog
$end
$timescale
	1ns
$end
$scope module exercise2_3_tb $end
$var wire 1 ! h $end
$var wire 1 " g $end
$var wire 1 # f $end
$var reg 1 $ x1 $end
$var reg 1 % x2 $end
$var reg 1 & x3 $end
$scope module test $end
$var wire 1 # f $end
$var wire 1 " g $end
$var wire 1 ! h $end
$var wire 1 ' i1 $end
$var wire 1 ( i3 $end
$var wire 1 ) i4 $end
$var wire 1 * i5 $end
$var wire 1 + j1 $end
$var wire 1 , j2 $end
$var wire 1 - j3 $end
$var wire 1 . j4 $end
$var wire 1 / j5 $end
$var wire 1 0 j6 $end
$var wire 1 1 j7 $end
$var wire 1 2 j8 $end
$var wire 1 $ x1 $end
$var wire 1 % x2 $end
$var wire 1 & x3 $end
$upscope $end
$upscope $end
$enddefinitions $end
#0
$dumpvars
12
11
00
1/
1.
0-
1,
1+
0*
1)
1(
1'
0&
0%
0$
0#
0"
0!
$end
#10
0)
0/
1&
#20
1!
02
1#
1-
1)
1/
0'
0,
0&
1%
#30
0)
0/
1&
#40
0!
12
01
1"
10
1)
1/
1,
0(
0+
0.
0&
0%
1$
#50
0#
0"
1*
0)
0/
1&
#60
1#
1"
0*
1)
1/
0,
0&
1%
#70
0#
0"
1*
0)
0/
1&
