Lab_2/exercise2_1.v
module exercise2_1(f, g, h, a, b, c);
input a, b, c;
output f, g, h;

// Given Expression
and(x1, b, c);
or(x2, a, x1);
and(x3, c, a);
or(x4, b, x3);
and(f, x2, x4);

// Using AND and OR gates
and(y1, a, b);
and(y2, b, c);
and(y3, a, c);
or(g, y1, y2, y3);

// Using NAND Gates only
nand(z1, a, b);
nand(z2, b, c);
nand(z3, a, c);
nand(h, z1, z2, z3);

endmodule

Lab_2/exercise2_1_tb.v
`timescale 1ns/1ns
`include "exercise2_1.v"

module exercise2_1_tb;

reg a, b, c;
wire f, g, h;

exercise2_1 test(f, g, h, a, b, c);
initial begin 
        $dumpfile("exercise2_1.vcd");
        $dumpvars(0, exercise2_1_tb);
        
        a = 0; b = 0; c = 0; #10;
        a = 0; b = 0; c = 1; #10;
        a = 0; b = 1; c = 0; #10;
        a = 0; b = 1; c = 1; #10;
        a = 1; b = 0; c = 0; #10;
        a = 1; b = 0; c = 1; #10;
        a = 1; b = 1; c = 0; #10;
        a = 1; b = 1; c = 1; #10;
        
        $display("Test Complete");
end 
endmodule

Lab_2/exercise2_1.vcd
$date
	Tue Aug 30 10:06:02 2022
$end
$version
	Icarus Verilog
$end
$timescale
	1ns
$end
$scope module exercise2_1_tb $end
$var wire 1 ! h $end
$var wire 1 " g $end
$var wire 1 # f $end
$var reg 1 $ a $end
$var reg 1 % b $end
$var reg 1 & c $end
$scope module test $end
$var wire 1 $ a $end
$var wire 1 % b $end
$var wire 1 & c $end
$var wire 1 # f $end
$var wire 1 " g $end
$var wire 1 ! h $end
$var wire 1 ' x1 $end
$var wire 1 ( x2 $end
$var wire 1 ) x3 $end
$var wire 1 * x4 $end
$var wire 1 + y1 $end
$var wire 1 , y2 $end
$var wire 1 - y3 $end
$var wire 1 . z1 $end
$var wire 1 / z2 $end
$var wire 1 0 z3 $end
$upscope $end
$upscope $end
$enddefinitions $end
#0
$dumpvars
10
1/
1.
0-
0,
0+
0*
0)
0(
0'
0&
0%
0$
0#
0"
0!
$end
#10
1&
#20
1*
0&
1%
#30
1#
1(
1"
1!
1'
1,
0/
1&
#40
0#
0"
0!
0'
0*
0,
1/
0&
0%
1$
#50
1#
1*
1"
1!
1)
1-
00
1&
#60
0)
0-
10
1+
0.
0&
1%
#70
1'
1)
1,
1-
0/
00
1&
