Lab_1/addexercise1.v
module addexercise1(a, b, c, f1, f2);
input a, b, c;
output f1, f2;
assign f1 = (a & (~c)) | (b & c) | ((~b) & (~c));
assign f2 = (a | (~b) | c) & (a | b | (~c)) & ((~a) | b | (~c));
endmodule

Lab_1/addexercise1_tb.v
`timescale 1ns/1ns
`include "addexercise1.v"

module addexercise1_tb;

reg a, b, c;
wire f1, f2;

addexercise1 test(a, b, c, f1, f2);
initial begin 
        $dumpfile("addexercise1.vcd");
        $dumpvars(0, addexercise1_tb);
        
        a = 0; b = 0; c = 0; #10;
        
        a = 0; b = 0; c = 1; #10;
        
        a = 0; b = 1; c = 0; #10;
        
        a = 0; b = 1; c = 1; #10;
        
        a = 1; b = 0; c = 0; #10;
        
        a = 1; b = 0; c = 1; #10;
        
        a = 1; b = 1; c = 0; #10;
        
        a = 1; b = 1; c = 1; #10;
        
        $display("Test Complete");
end
endmodule

Lab_1/addexercise1.vcd
$date
	Tue Aug 23 09:13:53 2022
$end
$version
	Icarus Verilog
$end
$timescale
	1ns
$end
$scope module addexercise1_tb $end
$var wire 1 ! f2 $end
$var wire 1 " f1 $end
$var reg 1 # a $end
$var reg 1 $ b $end
$var reg 1 % c $end
$scope module test $end
$var wire 1 # a $end
$var wire 1 $ b $end
$var wire 1 % c $end
$var wire 1 " f1 $end
$var wire 1 ! f2 $end
$upscope $end
$upscope $end
$enddefinitions $end
#0
$dumpvars
0%
0$
0#
1"
1!
$end
#10
0!
0"
1%
#20
0!
0%
1$
#30
1"
1!
1%
#40
0%
0$
1#
#50
0"
0!
1%
#60
1"
1!
0%
1$
#70
1%
