Lab_1/exercise2ii.v
module exercise2ii(a, b, c, d, f, g);
input a, b, c, d;
output f, g;

assign f = d ^ (~(a & b)) ^ c;
assign g = ~(b | c | d);

endmodule

Lab_1/exercise2ii_tb.v
`timescale 1ns/1ns
`include "exercise2ii.v"

module exercise2ii_tb;

reg a, b, c, d;
wire f, g;

exercise2ii test(a, b, c, d, f, g);
initial begin
        $dumpfile("exercise2ii.vcd");
        $dumpvars(0, exercise2ii_tb);
        
        a = 0; b = 0; c = 0; d = 0; #10;
        
        a = 0; b = 0; c = 0; d = 1; #10;
        
        a = 0; b = 0; c = 1; d = 0; #10;
        
        a = 0; b = 0; c = 1; d = 1; #10;
        
        a = 0; b = 1; c = 0; d = 0; #10;
       
        a = 0; b = 1; c = 0; d = 1; #10;
        
        a = 0; b = 1; c = 1; d = 0; #10;
        
        a = 0; b = 1; c = 1; d = 1; #10;
        
        a = 1; b = 0; c = 0; d = 0; #10;
        
        a = 1; b = 0; c = 0; d = 1; #10;
        
        a = 1; b = 0; c = 1; d = 0; #10;
        
        a = 1; b = 0; c = 1; d = 1; #10;
        
        a = 1; b = 1; c = 0; d = 0; #10;
        
        a = 1; b = 1; c = 0; d = 1; #10;
        
        a = 1; b = 1; c = 1; d = 0; #10;
        
        a = 1; b = 1; c = 1; d = 1; #10;
        
        $display("Test Complete");
end 
endmodule

Lab_1/exercise2ii.vcd
$date
	Tue Aug 23 09:43:50 2022
$end
$version
	Icarus Verilog
$end
$timescale
	1ns
$end
$scope module exercise2ii_tb $end
$var wire 1 ! g $end
$var wire 1 " f $end
$var reg 1 # a $end
$var reg 1 $ b $end
$var reg 1 % c $end
$var reg 1 & d $end
$scope module test $end
$var wire 1 # a $end
$var wire 1 $ b $end
$var wire 1 % c $end
$var wire 1 & d $end
$var wire 1 " f $end
$var wire 1 ! g $end
$upscope $end
$upscope $end
$enddefinitions $end
#0
$dumpvars
0&
0%
0$
0#
1"
1!
$end
#10
0"
0!
1&
#20
0"
0&
1%
#30
1"
1&
#40
1"
0&
0%
1$
#50
0"
1&
#60
0"
0&
1%
#70
1"
1&
#80
1!
1"
0&
0%
0$
1#
#90
0"
0!
1&
#100
0"
0&
1%
#110
1"
1&
#120
0"
0&
0%
1$
#130
1"
1&
#140
1"
0&
1%
#150
0"
1&
