Lab_1/exercise1i.v
module exercise1i(a, b, c, d, f);
input a, b, c, d;
output f;
and(x1, a, b);
or(x2, x1, c);
not(x3, x2);
and(x4, x3, d);
or(x5, x2, d);
and(f, x5, x4);
endmodule

Lab_1/exercise1i_tb.v
`timescale 1ns/1ns
`include "exercise1i.v"

module exercise1i_tb;

reg a, b, c, d;
wire f;

exercise1i test(a, b, c, d, f);
initial begin
        $dumpfile("exercise1i.vcd");
        $dumpvars(0, exercise1i_tb);
        
        a = 0; b = 0; c = 0; d = 0; #10;
        
        a = 0; b = 0; c = 0; d = 1; #10;
        
        a = 0; b = 0; c = 1; d = 0; #10;
        
        a = 0; b = 0; c = 1; d = 1; #10;
        
        a = 0; b = 1; c = 0; d = 0; #10;
       
        a = 0; b = 1; c = 0; d = 1; #10;
        
        a = 0; b = 1; c = 1; d = 0; #10;
        
        a = 0; b = 1; c = 1; d = 1; #10;
        
        a = 1; b = 0; c = 0; d = 0; #10;
        
        a = 1; b = 0; c = 0; d = 1; #10;
        
        a = 1; b = 0; c = 1; d = 0; #10;
        
        a = 1; b = 0; c = 1; d = 1; #10;
        
        a = 1; b = 1; c = 0; d = 0; #10;
        
        a = 1; b = 1; c = 0; d = 1; #10;
        
        a = 1; b = 1; c = 1; d = 0; #10;
        
        a = 1; b = 1; c = 1; d = 1; #10;
        
        $display("Test Complete");
end 
endmodule

Lab_1/exercise1i.vcd
$date
	Tue Aug 23 09:23:35 2022
$end
$version
	Icarus Verilog
$end
$timescale
	1ns
$end
$scope module exercise1i_tb $end
$var wire 1 ! f $end
$var reg 1 " a $end
$var reg 1 # b $end
$var reg 1 $ c $end
$var reg 1 % d $end
$scope module test $end
$var wire 1 " a $end
$var wire 1 # b $end
$var wire 1 $ c $end
$var wire 1 % d $end
$var wire 1 ! f $end
$var wire 1 & x1 $end
$var wire 1 ' x2 $end
$var wire 1 ( x3 $end
$var wire 1 ) x4 $end
$var wire 1 * x5 $end
$upscope $end
$upscope $end
$enddefinitions $end
#0
$dumpvars
0*
0)
1(
0'
0&
0%
0$
0#
0"
0!
$end
#10
1!
1)
1*
1%
#20
0!
0(
0)
1'
0%
1$
#30
1%
#40
1(
0*
0'
0%
0$
1#
#50
1!
1)
1*
1%
#60
0!
0(
0)
1'
0%
1$
#70
1%
#80
1(
0*
0'
0%
0$
0#
1"
#90
1!
1)
1*
1%
#100
0!
0(
0)
1'
0%
1$
#110
1%
#120
1&
0%
0$
1#
#130
1%
#140
0%
1$
#150
1%
