Lab_4/exercise1.v
module exercise1(f, a, b, c, d);
input a, b, c, d;
output f;
assign f = ~((~((~(a & (~(b & b)))) & (~(c & (~(d & d)))))) & (~((~(a & (~(b & b)))) & (~(c & (~(d & d)))))));
endmodule

Lab_4/exercise1_tb.v
`timescale 1ns/1ns
`include "exercise1.v"

module exercise1_tb();

reg a, b, c, d;
wire f;

exercise1 test(f, a, b, c, d);
initial begin
        $dumpfile("exercise1.vcd");
        $dumpvars(0, exercise1_tb);
        
        a = 0; b = 0; c = 0; d = 0; #10;
        a = 0; b = 0; c = 0; d = 1; #10;
        a = 0; b = 0; c = 1; d = 0; #10;
        a = 0; b = 0; c = 1; d = 1; #10;
        a = 0; b = 1; c = 0; d = 0; #10;
        a = 0; b = 1; c = 0; d = 1; #10;
        a = 0; b = 1; c = 1; d = 0; #10;
        a = 0; b = 1; c = 1; d = 1; #10;
        a = 1; b = 0; c = 0; d = 0; #10;
        a = 1; b = 0; c = 0; d = 1; #10;
        a = 1; b = 0; c = 1; d = 0; #10;
        a = 1; b = 0; c = 1; d = 1; #10;
        a = 1; b = 1; c = 0; d = 0; #10;
        a = 1; b = 1; c = 0; d = 1; #10;
        a = 1; b = 1; c = 1; d = 0; #10;
        a = 1; b = 1; c = 1; d = 1; #10;
               
        $display("Test Complete");
end
endmodule

Lab_4/exercise1.vcd
$date
	Tue Sep 13 10:06:46 2022
$end
$version
	Icarus Verilog
$end
$timescale
	1ns
$end
$scope module exercise1_tb $end
$var wire 1 ! f $end
$var reg 1 " a $end
$var reg 1 # b $end
$var reg 1 $ c $end
$var reg 1 % d $end
$scope module test $end
$var wire 1 " a $end
$var wire 1 # b $end
$var wire 1 $ c $end
$var wire 1 % d $end
$var wire 1 ! f $end
$upscope $end
$upscope $end
$enddefinitions $end
#0
$dumpvars
0%
0$
0#
0"
1!
$end
#10
1%
#20
0!
0%
1$
#30
1!
1%
#40
0%
0$
1#
#50
1%
#60
0!
0%
1$
#70
1!
1%
#80
0!
0%
0$
0#
1"
#90
1%
#100
0%
1$
#110
1%
#120
1!
0%
0$
1#
#130
1%
#140
0!
0%
1$
#150
1!
1%
