Lab_4/exercise2.v
module exercise2(f, a, b, c, d);
input a, b, c, d;
output f;
assign f = ~((~((~(a | c | (~(d | d)))) | (~(b | d)) | (~(b | c)))) | (~((~(a | c | (~(d | d)))) | (~(b | d)) | (~(b | c)))));
endmodule

Lab_4/exercise2_tb.v
`timescale 1ns/1ns
`include "exercise2.v"

module exercise2_tb();

reg a, b, c, d;
wire f;

exercise2 test(f, a, b, c, d);
initial begin
        $dumpfile("exercise2.vcd");
        $dumpvars(0, exercise2_tb);
        
        a = 0; b = 0; c = 0; d = 0; #10;
        a = 0; b = 0; c = 0; d = 1; #10;
        a = 0; b = 0; c = 1; d = 0; #10;
        a = 0; b = 0; c = 1; d = 1; #10;
        a = 0; b = 1; c = 0; d = 0; #10;
        a = 0; b = 1; c = 0; d = 1; #10;
        a = 0; b = 1; c = 1; d = 0; #10;
        a = 0; b = 1; c = 1; d = 1; #10;
        a = 1; b = 0; c = 0; d = 0; #10;
        a = 1; b = 0; c = 0; d = 1; #10;
        a = 1; b = 0; c = 1; d = 0; #10;
        a = 1; b = 0; c = 1; d = 1; #10;
        a = 1; b = 1; c = 0; d = 0; #10;
        a = 1; b = 1; c = 0; d = 1; #10;
        a = 1; b = 1; c = 1; d = 0; #10;
        a = 1; b = 1; c = 1; d = 1; #10;
               
        $display("Test Complete");
end
endmodule

Lab_4/exercise2.vcd
$date
	Tue Sep 13 09:27:34 2022
$end
$version
	Icarus Verilog
$end
$timescale
	1ns
$end
$scope module exercise2_tb $end
$var wire 1 ! f $end
$var reg 1 " a $end
$var reg 1 # b $end
$var reg 1 $ c $end
$var reg 1 % d $end
$scope module test $end
$var wire 1 " a $end
$var wire 1 # b $end
$var wire 1 $ c $end
$var wire 1 % d $end
$var wire 1 ! f $end
$upscope $end
$upscope $end
$enddefinitions $end
#0
$dumpvars
0%
0$
0#
0"
1!
$end
#10
1%
#20
0%
1$
#30
0!
1%
#40
0!
0%
0$
1#
#50
1!
1%
#60
0!
0%
1$
#70
1%
#80
1!
0%
0$
0#
1"
#90
1%
#100
1!
0%
1$
#110
0!
1%
#120
0%
0$
1#
#130
1%
#140
0%
1$
#150
1%
